.bzrignore
COPYING
ChangeLog
INSTALL.txt
Makefile
README.txt
TODO.txt
drilldown.wpr
setup.cfg
setup.py
docs/Makefile
docs/conf.py
docs/index.rst
docs/install.rst
docs/make.bat
docs/overview.rst
docs/templates.rst
docs/views.rst
softwarefabrica/__init__.py
softwarefabrica.django.drilldown.egg-info/PKG-INFO
softwarefabrica.django.drilldown.egg-info/SOURCES.txt
softwarefabrica.django.drilldown.egg-info/dependency_links.txt
softwarefabrica.django.drilldown.egg-info/namespace_packages.txt
softwarefabrica.django.drilldown.egg-info/not-zip-safe
softwarefabrica.django.drilldown.egg-info/requires.txt
softwarefabrica.django.drilldown.egg-info/top_level.txt
softwarefabrica/django/__init__.py
softwarefabrica/django/drilldown/__init__.py
softwarefabrica/django/drilldown/bzrcachedrev.py
softwarefabrica/django/drilldown/finddata.py
softwarefabrica/django/drilldown/models.py
softwarefabrica/django/drilldown/urls.py
softwarefabrica/django/drilldown/version.py
softwarefabrica/django/drilldown/views.py
softwarefabrica/django/drilldown/views.py.bkp
softwarefabrica/django/drilldown/templates/drilldown/object_drilldown.html
softwarefabrica/django/drilldown/tests/__init__.py
softwarefabrica/django/drilldown/tests/models.py
softwarefabrica/django/drilldown/tests/runner.py
softwarefabrica/django/drilldown/tests/settings.py
softwarefabrica/django/drilldown/tests/tests.py
softwarefabrica/django/drilldown/tests/urls.py
