Metadata-Version: 1.0
Name: softwarefabrica.django.drilldown
Version: 0.9dev-BZR-r3-panta-elasticworld.org-20091022181215-3nbknm8vmfpngs70
Summary: Drill-down navigation for django projects
Home-page: http://cheeseshop.python.org/pypi/softwarefabrica.django.drilldown/
Author: Marco Pantaleoni
Author-email: m.pantaleoni@softwarefabrica.org
License: GNU GPL v2
Download-URL: http://pypi.python.org/packages/source/s/softwarefabrica.django.drilldown/softwarefabrica.django.drilldown-0.9dev-BZR-r3-panta-elasticworld.org-20091022181215-3nbknm8vmfpngs70.tar.gz
Keywords: drill-down drilldown navigation browsing database django softwarefabrica
Platform: UNKNOWN
Classifier: Development Status :: 4 - Beta
Classifier: Framework :: Django
Classifier: Intended Audience :: Developers
Classifier: License :: OSI Approved :: GNU General Public License (GPL)
Classifier: Operating System :: OS Independent
Classifier: Programming Language :: Python :: 2.4
Classifier: Topic :: Software Development :: Libraries :: Python Modules
